scikit_fmm-2025.1.29.dist-info/METADATA
scikit_fmm-2025.1.29.dist-info/WHEEL
scikit_fmm-2025.1.29.dist-info/LICENSE.txt
skfmm/cfmm.cp310-win_amd64.pyd
skfmm/cfmm.cp310-win_amd64.lib
skfmm/pheap.cp310-win_amd64.pyd
skfmm/pheap.cp310-win_amd64.lib
skfmm/__init__.py
skfmm/pfmm.py
skfmm/heap.py
scikit_fmm-2025.1.29.dist-info/RECORD
