Metadata-Version: 2.1
Name: scikit-fmm
Version: 2025.1.29
Summary: An extension module implementing the fast marching method
Keywords: fast marching method,Eikonal equation,interface,boundary
Author-Email: Jason Furtney <jkfurtney@gmail.com>
License: Unless otherwise specified by LICENSE.txt files in individual
Classifier: Development Status :: 5 - Production/Stable
Classifier: License :: OSI Approved :: BSD License
Classifier: Operating System :: OS Independent
Classifier: Topic :: Scientific/Engineering
Classifier: Intended Audience :: Science/Research
Classifier: Programming Language :: C++
Classifier: Programming Language :: Python :: 3
Requires-Python: >=3.9
